{"name": "人力资源管理法规", "children": [{"name": "临时用工", "en": "contingent work force", "superfield": "管理科学技术"}, {"name": "事故预防", "en": "accident prevention", "superfield": "管理科学技术"}, {"name": "人事档案", "en": "personnel archive", "superfield": "管理科学技术"}, {"name": "人力资源法律体系", "en": "human resources legal system", "superfield": "管理科学技术"}, {"name": "伤残保险", "en": "disability insurance", "superfield": "管理科学技术"}, {"name": "公平就业机会", "en": "equal employment opportunity", "superfield": "管理科学技术"}, {"name": "共同决策制", "en": "co-determination system", "superfield": "管理科学技术"}, {"name": "劳务派遣服务", "en": "dispatch service", "superfield": "管理科学技术"}, {"name": "劳动关系", "en": "labor relationship", "superfield": "管理科学技术"}, {"name": "劳动关系顾问", "en": "labor relation consultant", "superfield": "管理科学技术"}, {"name": "劳动卫生法规", "en": "occupational health regulation", "superfield": "管理科学技术"}, {"name": "劳动合同", "en": "labor contract", "superfield": "管理科学技术"}, {"name": "劳动安全法规", "en": "occupational safety regulation", "superfield": "管理科学技术"}, {"name": "劳动歧视", "en": "labor discrimination", "superfield": "管理科学技术"}, {"name": "劳动法", "en": "labor law", "superfield": "管理科学技术"}, {"name": "劳动监察员", "en": "labor supervisor", "superfield": "管理科学技术"}, {"name": "劳动监督检查", "en": "labor supervision and inspection", "superfield": "管理科学技术"}, {"name": "劳动管理", "en": "labor management", "superfield": "管理科学技术"}, {"name": "劳动纠纷", "en": "labor dispute", "superfield": "管理科学技术"}, {"name": "劳动纪律", "en": "labor discipline", "superfield": "管理科学技术"}]}