{"name": "代数K理论", "children": [{"name": "代数K理论", "en": "algebraic K theory", "superfield": "数学"}, {"name": "保积函子", "en": "product-preserving functor", "superfield": "数学"}, {"name": "共尾保积函子", "en": "cofinal product-preserving functor", "superfield": "数学"}, {"name": "可逆模", "en": "invertible module", "superfield": "数学"}, {"name": "带积合成范畴", "en": "category with product and com- position", "superfield": "数学"}, {"name": "带积范畴", "en": "category with product", "superfield": "数学"}, {"name": "常数秩模", "en": "module of constant rank", "superfield": "数学"}, {"name": "怀特黑德群", "en": "Whitehead group", "superfield": "数学"}, {"name": "施坦贝格关系", "en": "Steinberg relations", "superfield": "数学"}, {"name": "施坦贝格群", "en": "Steinberg group", "superfield": "数学"}, {"name": "格罗滕迪克群", "en": "Grothendieck group", "superfield": "数学"}, {"name": "环的怀特黑德群", "en": "Whitehead group of a ring", "superfield": "数学"}, {"name": "环的施坦贝格群", "en": "Steinberg group of a ring", "superfield": "数学"}, {"name": "环的格罗滕迪克群", "en": "Grothendieck group of a ring", "superfield": "数学"}, {"name": "约化格罗滕迪克群", "en": "reduced Grothendieck group", "superfield": "数学"}, {"name": "行列式映射", "en": "determinant mapping", "superfield": "数学"}, {"name": "连通环", "en": "connected ring", "superfield": "数学"}, {"name": "阿贝尔化函子", "en": "abelianizing functor", "superfield": "数学"}]}