{"name": "免疫学检测和诊断", "children": [{"name": "DNA甲基化", "en": "DNA methylation", "superfield": "免疫学"}, {"name": "DNA芯片", "en": "DNA chip", "superfield": "免疫学"}, {"name": "Raji细胞法", "en": "Raji cell assay", "superfield": "免疫学"}, {"name": "TUNEL检测", "en": "terminal deoxynucleotidyl transferase-mediated dUTP-biotin nick end labeling assay", "superfield": "免疫学"}, {"name": "Winn试验", "en": "Winn test", "superfield": "免疫学"}, {"name": "中和试验", "en": "neutralization test", "superfield": "免疫学"}, {"name": "乳环状试验", "en": "milk ring test", "superfield": "免疫学"}, {"name": "乳胶凝集试验", "en": "latex agglutination test", "superfield": "免疫学"}, {"name": "交叉免疫电泳", "en": "crossed immunoelectrophoresis", "superfield": "免疫学"}, {"name": "亲和标记", "en": "affinity labeling", "superfield": "免疫学"}, {"name": "位点专一诱变", "en": "site-directed mutagenesis", "superfield": "免疫学"}, {"name": "克韦姆试验", "en": "Kveim test", "superfield": "免疫学"}, {"name": "免疫亲和层析", "en": "immune affinity chromatography", "superfield": "免疫学"}, {"name": "免疫固定电泳", "en": "immunofixation electrophoresis", "superfield": "免疫学"}, {"name": "免疫放射测定", "en": "immunoradiometric assay", "superfield": "免疫学"}, {"name": "免疫标记技术", "en": "immunolabeling technique", "superfield": "免疫学"}, {"name": "免疫比浊法", "en": "immunonephelometry", "superfield": "免疫学"}, {"name": "免疫溶血", "en": "immune hemolysis", "superfield": "免疫学"}, {"name": "免疫珠试验", "en": "immunobead test", "superfield": "免疫学"}, {"name": "免疫电泳", "en": "immunoelectrophoresis", "superfield": "免疫学"}]}