{"name": "其他有色金属及其合金", "children": [{"name": "人造金刚石触媒用镍合金", "en": "nickel alloy for artificial diamond", "superfield": "材料科学技术"}, {"name": "哈氏合金", "en": "Hastelloy alloy", "superfield": "材料科学技术"}, {"name": "火花塞电极镍合金", "en": "sparking plug electrode nickel alloy", "superfield": "材料科学技术"}, {"name": "电镀用阳极镍", "en": "electroplating anodic nickel", "superfield": "材料科学技术"}, {"name": "耐蚀镍合金", "en": "corrosion resistant nickel alloy", "superfield": "材料科学技术"}, {"name": "莫内尔合金", "en": "Monel alloy", "superfield": "材料科学技术"}, {"name": "钴", "en": "cobalt", "superfield": "材料科学技术"}, {"name": "钴基合金", "en": "cobalt based alloy", "superfield": "材料科学技术"}, {"name": "钴基轴尖合金", "en": "cobalt based axle alloy", "superfield": "材料科学技术"}, {"name": "镍", "en": "nickel", "superfield": "材料科学技术"}, {"name": "镍合金", "en": "nickel alloy", "superfield": "材料科学技术"}]}