{"name": "分析仪器", "children": [{"name": "光学式分析仪器", "children": [{"name": "光学式分析仪器一般名词"}, {"name": "光学式分析仪器仪器和附件"}, {"name": "光学式分析仪器分析原理"}]}, {"name": "分析仪器一般名词", "children": [{"name": "光学[式]分析仪器", "en": "optical analytical instrument", "superfield": "机械工程"}, {"name": "分析仪器", "en": "analytical instrument", "superfield": "机械工程"}, {"name": "定性分析", "en": "qualitative analysis", "superfield": "机械工程"}, {"name": "定量分析", "en": "quantitative analysis", "superfield": "机械工程"}, {"name": "常量分析", "en": "macro-analysis", "superfield": "机械工程"}, {"name": "微量分析", "en": "micro-analysis", "superfield": "机械工程"}, {"name": "波谱仪器", "en": "wave spectrometer", "superfield": "机械工程"}, {"name": "热学[式]分析仪器", "en": "thermometric analyzer", "superfield": "机械工程"}, {"name": "物性分析仪器", "en": "analyzer for physical property", "superfield": "机械工程"}, {"name": "电化学[式]分析仪器", "en": "electrochemical analyzer", "superfield": "机械工程"}, {"name": "痕量分析", "en": "trace analysis", "superfield": "机械工程"}, {"name": "能谱和射线分析仪器", "en": "spectroscope and ray analyzer", "superfield": "机械工程"}, {"name": "质谱仪器", "en": "mass spectrometer", "superfield": "机械工程"}]}, {"name": "波谱仪器", "children": [{"name": "波谱仪器一般名词"}, {"name": "波谱仪器仪器和附件"}, {"name": "波谱仪器分析原理"}]}, {"name": "热学式分析仪器", "children": [{"name": "热学式分析仪器一般名词"}, {"name": "热学式分析仪器仪器和附件"}, {"name": "热学式分析仪器分析原理"}]}, {"name": "物性分析仪器", "children": [{"name": "物性分析仪器一般名词"}, {"name": "物性分析仪器仪器和附件"}, {"name": "物性分析仪器分析原理"}]}, {"name": "环境分析仪", "children": [{"name": "二氧化硫分析仪", "en": "sulfur dioxide analyzer", "superfield": "机械工程"}, {"name": "农用分析仪", "en": "agricultural analyzer", "superfield": "机械工程"}, {"name": "动态校准器", "en": "dynamic calibrator", "superfield": "机械工程"}, {"name": "反应气", "en": "reaction gas", "superfield": "机械工程"}, {"name": "尘量分析仪", "en": "dust analyzer", "superfield": "机械工程"}, {"name": "气体发生器", "en": "gas generator", "superfield": "机械工程"}, {"name": "氮氧化物分析仪", "en": "nitrogen-oxide analyzer", "superfield": "机械工程"}, {"name": "水质分析仪", "en": "water quality analyzer", "superfield": "机械工程"}, {"name": "渗透管", "en": "permeability tube", "superfield": "机械工程"}, {"name": "环境气体分析仪", "en": "environmental gas analyzer", "superfield": "机械工程"}, {"name": "环境监测站", "en": "environmental monitor station", "superfield": "机械工程"}, {"name": "生物医学分析仪", "en": "biomedical analyzer", "superfield": "机械工程"}, {"name": "电导[式]分析器", "en": "conductometric analyzer", "superfield": "机械工程"}, {"name": "臭氧分析仪", "en": "ozone analyzer", "superfield": "机械工程"}, {"name": "采样器", "en": "sampler", "superfield": "机械工程"}, {"name": "食品分析仪", "en": "food analyzer", "superfield": "机械工程"}]}, {"name": "电化学式分析仪器", "children": [{"name": "电化学式分析仪器一般名词"}, {"name": "电化学式分析仪器仪器和附件"}, {"name": "电化学式分析仪器分析原理"}]}, {"name": "能谱和射线分析仪器", "children": [{"name": "能谱和射线分析仪器一般名词"}, {"name": "能谱和射线分析仪器仪器和附件"}, {"name": "能谱和射线分析仪器分析原理"}]}, {"name": "色谱仪器", "children": [{"name": "色谱仪器一般名词"}, {"name": "色谱仪器仪器和附件"}, {"name": "色谱仪器分析原理"}]}, {"name": "质谱仪器", "children": [{"name": "质谱仪器一般名词"}, {"name": "质谱仪器仪器和附件"}, {"name": "质谱仪器测量原理"}]}]}