{"name": "固溶体半导体材料", "children": [{"name": "固溶体半导体材料", "en": "semiconducting solid solution materials", "superfield": "材料科学技术"}, {"name": "碲锌镉", "en": "zinc cadmium telluride", "superfield": "材料科学技术"}, {"name": "碲锡铅", "en": "lead tin telluride", "superfield": "材料科学技术"}, {"name": "碲镉汞", "en": "mercury cadmium telluride", "superfield": "材料科学技术"}, {"name": "铟砷磷", "en": "indium arsenide phosphide", "superfield": "材料科学技术"}, {"name": "铟镓氮", "en": "indium gallium nitride", "superfield": "材料科学技术"}, {"name": "镓砷磷", "en": "gallium arsenic phosphide", "superfield": "材料科学技术"}, {"name": "镓铝砷", "en": "aluminium gallium arsenide", "superfield": "材料科学技术"}, {"name": "镓铟砷", "en": "gallium indium arsenide", "superfield": "材料科学技术"}, {"name": "镓铟砷磷", "en": "gallium indium arsenide phosphide", "superfield": "材料科学技术"}, {"name": "镓铟砷锑", "en": "gallium indium arsenide antimonide", "superfield": "材料科学技术"}, {"name": "镓铟磷", "en": "gallium indium phosphide", "superfield": "材料科学技术"}, {"name": "镓铟铝氮", "en": "aluminium gallium indium nitride", "superfield": "材料科学技术"}]}