{"name": "城市绿地", "children": [{"name": "专类公园", "en": "specific garden", "superfield": "建筑学"}, {"name": "儿童公园", "en": "children’s park", "superfield": "建筑学"}, {"name": "公园", "en": "park", "superfield": "建筑学"}, {"name": "动物园", "en": "zoo", "superfield": "建筑学"}, {"name": "历史名园", "en": "historical garden and park", "superfield": "建筑学"}, {"name": "墓园", "en": "cemetery", "superfield": "建筑学"}, {"name": "居住绿地", "en": "green space attached to housing estate", "superfield": "建筑学"}, {"name": "岩石园", "en": "rock garden", "superfield": "建筑学"}, {"name": "带状公园", "en": "linear park", "superfield": "建筑学"}, {"name": "植物园", "en": "botanical garden", "superfield": "建筑学"}, {"name": "生产绿地", "en": "productive plantation area", "superfield": "建筑学"}, {"name": "盆景园", "en": "penjing garden", "superfield": "建筑学"}, {"name": "盲人公园", "en": "blind’s garden", "superfield": "建筑学"}, {"name": "社区公园", "en": "community park", "superfield": "建筑学"}, {"name": "纪念公园", "en": "commemorative park", "superfield": "建筑学"}, {"name": "花园", "en": "garden", "superfield": "建筑学"}, {"name": "街旁绿地", "en": "roadside green space", "superfield": "建筑学"}, {"name": "道路绿地", "en": "green space attached to urban road and square", "superfield": "建筑学"}, {"name": "附属绿地", "en": "attached green space", "superfield": "建筑学"}, {"name": "风景名胜公园", "en": "famous scenic park", "superfield": "建筑学"}]}