{"name": "城市设计", "children": [{"name": "临街面", "en": "frontage", "superfield": "建筑学"}, {"name": "城市体形环境", "en": "urban physical environment", "superfield": "建筑学"}, {"name": "城市公共设施", "en": "urban public facility", "superfield": "建筑学"}, {"name": "城市公共领域", "en": "urban public realm", "superfield": "建筑学"}, {"name": "城市天际线", "en": "city skyline", "superfield": "建筑学"}, {"name": "城市广场", "en": "city square", "superfield": "建筑学"}, {"name": "城市形态", "en": "urban morphology", "superfield": "建筑学"}, {"name": "城市意象", "en": "city image", "superfield": "建筑学"}, {"name": "城市照明", "en": "urban lighting", "superfield": "建筑学"}, {"name": "城市美学", "en": "urban aesthetics", "superfield": "建筑学"}, {"name": "城市肌理", "en": "urban tissue", "superfield": "建筑学"}, {"name": "城市色彩", "en": "city color", "superfield": "建筑学"}, {"name": "城市设计", "en": "urban design", "superfield": "建筑学"}, {"name": "城市设计导则", "en": "urban design guideline", "superfield": "建筑学"}, {"name": "城市雕塑", "en": "urban sculpture", "superfield": "建筑学"}, {"name": "城镇景观", "en": "townscape", "superfield": "建筑学"}, {"name": "整体城市设计", "en": "integrated urban design", "superfield": "建筑学"}, {"name": "文脉", "en": "context", "superfield": "建筑学"}, {"name": "林荫道", "en": "parkway", "superfield": "建筑学"}, {"name": "步行系统", "en": "pedestrian system", "superfield": "建筑学"}]}