{"name": "概率空间", "children": [{"name": "[集]半环", "en": "semi-ring of sets", "superfield": "数学"}, {"name": "λ系", "en": "λ-system", "superfield": "数学"}, {"name": "π系", "en": "π-system", "superfield": "数学"}, {"name": "不可能事件", "en": "impossible event", "superfield": "数学"}, {"name": "不相容事件", "en": "mutually exclusive events", "superfield": "数学"}, {"name": "两两独立[的]", "en": "pairwise independent", "superfield": "数学"}, {"name": "事件σ域", "en": "σ-field of events", "superfield": "数学"}, {"name": "事件域", "en": "field of events", "superfield": "数学"}, {"name": "事件指示函数", "en": "indicator function of an event", "superfield": "数学"}, {"name": "事件的交", "en": "intersection of events", "superfield": "数学"}, {"name": "事件的对称差", "en": "symmetric difference of events", "superfield": "数学"}, {"name": "事件的差", "en": "difference of events", "superfield": "数学"}, {"name": "事件的并", "en": "union of events", "superfield": "数学"}, {"name": "事件的蕴含", "en": "implication of events", "superfield": "数学"}, {"name": "事件的补", "en": "complement of an event", "superfield": "数学"}, {"name": "伯努利试验", "en": "Bernoulli trials", "superfield": "数学"}, {"name": "全概率公式", "en": "total probability formula", "superfield": "数学"}, {"name": "几乎必然", "en": "almost sure", "superfield": "数学"}, {"name": "几何概率", "en": "geometric probability", "superfield": "数学"}, {"name": "单调类", "en": "monotone class", "superfield": "数学"}]}