{"name": "气候环境试验设备零部件及附件", "children": [{"name": "人工光源", "en": "artificial light source", "superfield": "机械工程"}, {"name": "加湿器", "en": "humidifier", "superfield": "机械工程"}, {"name": "加热器", "en": "heater", "superfield": "机械工程"}, {"name": "喷雾装置", "en": "spraying device", "superfield": "机械工程"}, {"name": "换气装置", "en": "breather", "superfield": "机械工程"}, {"name": "搅拌器", "en": "stirrer", "superfield": "机械工程"}, {"name": "温度控制器", "en": "temperature controller", "superfield": "机械工程"}, {"name": "温度程序控制器", "en": "programme regulator for temperature", "superfield": "机械工程"}, {"name": "温湿度控制器", "en": "temperature and humidity controller", "superfield": "机械工程"}, {"name": "湿度控制器", "en": "humidity controller", "superfield": "机械工程"}, {"name": "盐雾发生装置", "en": "salt spray generator", "superfield": "机械工程"}, {"name": "盐雾过滤器", "en": "salt spray filter", "superfield": "机械工程"}, {"name": "空气过滤器", "en": "air filter", "superfield": "机械工程"}, {"name": "调节器", "en": "regulator", "superfield": "机械工程"}, {"name": "辐射元件", "en": "radiant element", "superfield": "机械工程"}, {"name": "远红外辐射器", "en": "far infrared radiator", "superfield": "机械工程"}, {"name": "降雨装置", "en": "rainer", "superfield": "机械工程"}, {"name": "除湿器", "en": "dehumidifier", "superfield": "机械工程"}, {"name": "鼓风装置", "en": "blower device", "superfield": "机械工程"}]}