{"name": "激光技术", "children": [{"name": "Q开关", "en": "Q-switch", "superfield": "机械工程"}, {"name": "偏振调制器", "en": "light polarization modulator", "superfield": "机械工程"}, {"name": "光伏效应", "en": "photovoltaic effect", "superfield": "机械工程"}, {"name": "光偏转", "en": "light deflection", "superfield": "机械工程"}, {"name": "光参量振荡", "en": "optical parametric oscillation", "superfield": "机械工程"}, {"name": "光参量放大", "en": "optical parametric amplification", "superfield": "机械工程"}, {"name": "光子牵引效应", "en": "photon drag effect", "superfield": "机械工程"}, {"name": "光弹效应", "en": "photo-elastic effect", "superfield": "机械工程"}, {"name": "光强调制器", "en": "light intensity modulator", "superfield": "机械工程"}, {"name": "光电导效应", "en": "photoconductive effect", "superfield": "机械工程"}, {"name": "光磁电效应", "en": "photomagnetoelectric effect", "superfield": "机械工程"}, {"name": "光调制器", "en": "optical modulator", "superfield": "机械工程"}, {"name": "内调制", "en": "internal modulation", "superfield": "机械工程"}, {"name": "动静比", "en": "output ratio of Q-switching to free running", "superfield": "机械工程"}, {"name": "声光Q开关", "en": "acoustooptic Q-switch", "superfield": "机械工程"}, {"name": "声光调制器", "en": "acoustooptic modulator", "superfield": "机械工程"}, {"name": "外光电效应", "en": "external photoelectric effect", "superfield": "机械工程"}, {"name": "外调制", "en": "external modulation", "superfield": "机械工程"}, {"name": "布拉格条件", "en": "Bragg condition", "superfield": "机械工程"}, {"name": "布拉格衍射", "en": "Bragg diffraction", "superfield": "机械工程"}]}