{"name": "航空器维修工程", "children": [{"name": "二次损伤", "en": "secondary damage", "superfield": "航空科学技术"}, {"name": "使用前大纲", "en": "prior-to-service program", "superfield": "航空科学技术"}, {"name": "使用检查", "en": "service inspection", "superfield": "航空科学技术"}, {"name": "偶然失效期", "en": "chance failure period", "superfield": "航空科学技术"}, {"name": "共模故障", "en": "common mode fault", "superfield": "航空科学技术"}, {"name": "分解检查", "en": "teardown inspection", "superfield": "航空科学技术"}, {"name": "到寿件", "en": "life-limit element", "superfield": "航空科学技术"}, {"name": "力谱小时", "en": "spectrum hours", "superfield": "航空科学技术"}, {"name": "功能性故障", "en": "functional fault", "superfield": "航空科学技术"}, {"name": "功能检查", "en": "function inspection", "superfield": "航空科学技术"}, {"name": "区域检查", "en": "zonal-installation inspection", "superfield": "航空科学技术"}, {"name": "危险性故障", "en": "critical fault", "superfield": "航空科学技术"}, {"name": "原位维修", "en": "on-site maintenance", "superfield": "航空科学技术"}, {"name": "参数监控", "en": "parameter monitoring", "superfield": "航空科学技术"}, {"name": "可靠性指标", "en": "reliability index", "superfield": "航空科学技术"}, {"name": "多重故障", "en": "multiple fault", "superfield": "航空科学技术"}, {"name": "定时监测", "en": "periodic monitor", "superfield": "航空科学技术"}, {"name": "定期维修", "en": "periodic maintenance", "superfield": "航空科学技术"}, {"name": "巡视检查", "en": "walkaround inspection", "superfield": "航空科学技术"}, {"name": "工作有效度", "en": "work effectiveness", "superfield": "航空科学技术"}]}